[
    {
        "level2":  "Thuộc công thức chuẩn, thực hiện ổn định với đa số sản phẩm",
        "definition":  "Hiểu và thực hiện các công thức đồ uống theo chuẩn Highlands",
        "id":  "COMP01",
        "level4":  "Là “chuẩn mực sống động”, phát hiện sai lệch nhỏ \u0026 điều chỉnh ngay",
        "category":  "Technical / Operational",
        "nameVi":  "Am hiểu công thức \u0026 Gold Standard",
        "name":  "Am hiểu công thức \u0026 Gold Standard",
        "evidence":  "Quan sát thực hành, kiểm tra định kỳ theo checklist",
        "trainingMethod":  "On-the-job training, shadowing MB, refresher session",
        "level1":  "Biết các công thức cơ bản, cần hỗ trợ giám sát",
        "level3":  "Thực hiện chính xác, training lại cho Barista mới"
    },
    {
        "level2":  "Tự lập trình và điều chỉnh các chế độ chuẩn",
        "definition":  "Kỹ năng thiết lập và điều chỉnh máy pha espresso",
        "id":  "COMP02",
        "level4":  "Huấn luyện bar, đề xuất cải tiến máy",
        "category":  "Technical / Operational",
        "nameVi":  "Espresso machine setting up and adjusting skills",
        "name":  "Espresso machine setting up and adjusting skills",
        "evidence":  "Quan sát thao tác, log, liên hệ kỹ thuật bảo trì",
        "trainingMethod":  "Demo máy, SOP training, coaching",
        "level1":  "Biết cách bật/tắt, vận hành cơ bản dưới hướng dẫn",
        "level3":  "Khắc phục lỗi nhỏ, hỗ trợ Barista mới"
    },
    {
        "level2":  "Pha ổn định, đúng chuẩn hương vị",
        "definition":  "Kỹ năng pha chế espresso đúng chuẩn",
        "id":  "COMP03",
        "level4":  "Là trainer espresso",
        "category":  "Technical / Operational",
        "nameVi":  "Espresso coffee making skill",
        "name":  "Espresso coffee making skill",
        "evidence":  "Blind tasting, kết quả audit, phản hồi khách hàng",
        "trainingMethod":  "On-the-job training, tasting session",
        "level1":  "Pha được các loại cơ bản theo hướng dẫn",
        "level3":  "Huấn luyện Barista mới pha chuẩn"
    },
    {
        "level2":  "Đánh sữa đúng độ mịn, nhiệt độ chuẩn",
        "definition":  "Kỹ năng đánh sữa nóng, tạo bọt sữa",
        "id":  "COMP04",
        "level4":  "Huấn luyện latte art, sáng tạo đồ uống",
        "category":  "Technical / Operational",
        "nameVi":  "Milk steaming and frothing skills",
        "name":  "Milk steaming and frothing skills",
        "evidence":  "Quan sát, sản phẩm thực tế",
        "trainingMethod":  "Coaching, tham gia workshop latte art",
        "level1":  "Biết đánh sữa cơ bản",
        "level3":  "Hướng dẫn Barista mới, tạo latte art đơn giản"
    },
    {
        "level2":  "Thực hiện đầy đủ, đúng chuẩn",
        "definition":  "Vệ sinh máy espresso đúng quy trình",
        "id":  "COMP05",
        "level4":  "Huấn luyện chuẩn vệ sinh máy toàn bar",
        "category":  "Technical / Operational",
        "nameVi":  "Espresso machine cleaning skill",
        "name":  "Espresso machine cleaning skill",
        "evidence":  "Quan sát thao tác, checklist vệ sinh",
        "trainingMethod":  "SOP training, shadow MB",
        "level1":  "Thực hiện vệ sinh cơ bản theo hướng dẫn",
        "level3":  "Giám sát, nhắc nhở đồng đội"
    },
    {
        "level2":  "Thực hiện định kỳ, đúng quy trình (1-2 tháng/1 lần)",
        "definition":  "Vệ sinh máy xay cà phê",
        "id":  "COMP06",
        "level4":  "Huấn luyện toàn bar, chuẩn SOP",
        "category":  "Technical / Operational",
        "nameVi":  "Coffee grinder cleaning skill",
        "name":  "Coffee grinder cleaning skill",
        "evidence":  "Quan sát, checklist vệ sinh",
        "trainingMethod":  "Demo, SOP, coaching",
        "level1":  "Biết vệ sinh cơ bản",
        "level3":  "Nhắc nhở, hỗ trợ đồng đội"
    },
    {
        "level2":  "Pha ổn định",
        "definition":  "Pha chế cà phê truyền thống",
        "id":  "COMP07",
        "level4":  "Sáng tạo biến thể mới, huấn luyện khu vực",
        "category":  "Technical / Operational",
        "nameVi":  "Traditional coffee making skill",
        "name":  "Traditional coffee making skill",
        "evidence":  "Quan sát thực hành",
        "trainingMethod":  "Workshop, on-the-job",
        "level1":  "Thực hiện theo hướng dẫn",
        "level3":  "Huấn luyện Barista mới"
    },
    {
        "level2":  "Pha chuẩn, ổn định",
        "definition":  "Pha chế sản phẩm trà",
        "id":  "COMP08",
        "level4":  "Tham gia phát triển menu mới",
        "category":  "Technical / Operational",
        "nameVi":  "Tea making skill",
        "name":  "Tea making skill",
        "evidence":  "Quan sát, kết quả audit, phản hồi khách hàng",
        "trainingMethod":  "Shadowing, coaching",
        "level1":  "Biết các loại cơ bản",
        "level3":  "Hướng dẫn Barista mới"
    },
    {
        "level2":  "Thực hiện ổn định, đúng chuẩn",
        "definition":  "Pha chế đồ uống đá xay",
        "id":  "COMP09",
        "level4":  "Sáng tạo sản phẩm mới, huấn luyện bar",
        "category":  "Technical / Operational",
        "nameVi":  "Ice-blender drink making skill",
        "name":  "Ice-blender drink making skill",
        "evidence":  "Quan sát sản phẩm",
        "trainingMethod":  "On-the-job, demo",
        "level1":  "Thực hiện theo công thức",
        "level3":  "Hướng dẫn Barista mới"
    },
    {
        "level2":  "Kiểm tra và đảm bảo tươi mới",
        "definition":  "Nhận biết độ tươi mới của nguyên liệu",
        "id":  "COMP10",
        "level4":  "Huấn luyện kiểm tra, xây SOP",
        "category":  "Technical / Operational",
        "nameVi":  "Have knowledge about products\u0027 freshness",
        "name":  "Have knowledge about products\u0027 freshness",
        "evidence":  "Kiểm tra hàng ngày",
        "trainingMethod":  "Coaching, SOP",
        "level1":  "Nhận biết cơ bản",
        "level3":  "Nhắc nhở đồng đội"
    },
    {
        "level2":  "Trang trí đẹp, đúng chuẩn",
        "definition":  "Trang trí đồ uống theo chuẩn",
        "id":  "COMP11",
        "level4":  "Huấn luyện khu vực, phát triển chuẩn",
        "category":  "Technical / Operational",
        "nameVi":  "Drink decoration following standard",
        "name":  "Drink decoration following standard",
        "evidence":  "Quan sát sản phẩm",
        "trainingMethod":  "On-the-job, workshop",
        "level1":  "Trang trí cơ bản theo hướng dẫn",
        "level3":  "Hướng dẫn Barista mới"
    },
    {
        "level2":  "Hoàn thành nhanh, ổn định",
        "definition":  "Thực hiện công việc nhanh, hiệu quả",
        "id":  "COMP12",
        "level4":  "Tạo flow, hướng dẫn bar toàn khu vực",
        "category":  "Behavioral/ Performance competencies",
        "nameVi":  "Speed and efficiency in work",
        "name":  "Speed and efficiency in work",
        "evidence":  "Quan sát, thời gian làm việc",
        "trainingMethod":  "On-the-job, coaching",
        "level1":  "Thực hiện đủ công việc theo hướng dẫn",
        "level3":  "Tối ưu quy trình làm việc"
    },
    {
        "level2":  "Thân thiện, khách hàng hài lòng",
        "definition":  "Thái độ thân thiện, nhiệt tình",
        "id":  "COMP13",
        "level4":  "Là hình mẫu thái độ, coaching đội nhóm",
        "category":  "Behavioral/ Performance competencies",
        "nameVi":  "Friendly manner",
        "name":  "Friendly manner",
        "evidence":  "Quan sát, feedback khách",
        "trainingMethod":  "Roleplay, feedback",
        "level1":  "Tương tác cơ bản với khách \u0026 đồng nghiệp",
        "level3":  "Lan tỏa thái độ tích cực"
    },
    {
        "level2":  "Hợp tác hiệu quả, hỗ trợ đồng đội",
        "definition":  "Hợp tác nhóm",
        "id":  "COMP14",
        "level4":  "Tạo văn hóa teamwork, huấn luyện nhóm",
        "category":  "Behavioral/ Performance competencies",
        "nameVi":  "Team-work",
        "name":  "Team-work",
        "evidence":  "Quan sát teamwork",
        "trainingMethod":  "Coaching, shadowing",
        "level1":  "Làm việc nhóm cơ bản",
        "level3":  "Điều phối nhóm"
    },
    {
        "level2":  "Trao đổi rõ ràng với SM \u0026 team",
        "definition":  "Trao đổi thông tin hiệu quả",
        "id":  "COMP15",
        "level4":  "Kết nối Training ",
        "category":  "Behavioral/ Performance competencies",
        "nameVi":  "Communicate effectively",
        "name":  "Communicate effectively",
        "evidence":  "Quan sát thực tế, feedback team",
        "trainingMethod":  "Workshop, roleplay",
        "level1":  "Giao tiếp nhóm nhỏ",
        "level3":  "Xử lý xung đột nội bộ"
    },
    {
        "level2":  "Chủ động báo cáo, phản hồi",
        "definition":  "Báo cáo, trao đổi với cấp trên",
        "id":  "COMP16",
        "level4":  "Huấn luyện toàn bar, coaching",
        "category":  "Behavioral/ Performance competencies",
        "nameVi":  "Report and communicate to supervisor proactively",
        "name":  "Report and communicate to supervisor proactively",
        "evidence":  "Quan sát, feedback SM",
        "trainingMethod":  "Coaching, shadowing",
        "level1":  "Báo cáo theo hướng dẫn",
        "level3":  "Đánh giá kết quả nhóm"
    },
    {
        "level2":  "Chính xác hầu hết công việc",
        "definition":  "Thực hiện công việc chính xác",
        "id":  "COMP17",
        "level4":  "Huấn luyện chính xác cho team",
        "category":  "Behavioral/ Performance competencies",
        "nameVi":  "High degree of accuracy in work",
        "name":  "High degree of accuracy in work",
        "evidence":  "Quan sát, feedback SM",
        "trainingMethod":  "Coaching, checklist",
        "level1":  "Theo hướng dẫn",
        "level3":  "Giám sát đồng đội"
    },
    {
        "level2":  "Đúng giờ, quản lý thời gian tốt",
        "definition":  "Tuân thủ giờ giấc",
        "id":  "COMP18",
        "level4":  "Truyền cảm hứng văn hóa Highlands quản lý thời gian",
        "category":  "Behavioral/ Performance competencies",
        "nameVi":  "On time",
        "name":  "On time",
        "evidence":  "Attendance log, random check",
        "trainingMethod":  "Coaching",
        "level1":  "Đúng giờ cơ bản",
        "level3":  "Giám sát team"
    },
    {
        "level2":  "Điều phối nhóm nhỏ",
        "definition":  "Điều phối quầy hiệu quả",
        "id":  "COMP19",
        "level4":  "Xây dựng flow chuẩn, huấn luyện bar",
        "category":  "Behavioral/ Performance competencies",
        "nameVi":  "Smooth bar management and coordination",
        "name":  "Smooth bar management and coordination",
        "evidence":  "Quan sát ca làm việc",
        "trainingMethod":  "On-the-job, coaching",
        "level1":  "Hỗ trợ MB",
        "level3":  "Điều phối bar toàn ca"
    },
    {
        "level2":  "Chủ động duy trì",
        "definition":  "Vệ sinh cá nhân: tóc, móng, không đeo trang sức",
        "id":  "COMP20",
        "level4":  "Là hình mẫu, huấn luyện chuẩn",
        "category":  "Hygiene \u0026 Bar Standards",
        "nameVi":  "Personal hygiene",
        "name":  "Personal hygiene",
        "evidence":  "Quan sát thực tế, kết quả audit cửa hàng: QC, DM/SWATT",
        "trainingMethod":  "SOP training, coaching",
        "level1":  "Tuân thủ cơ bản",
        "level3":  "Nhắc nhở đồng đội"
    },
    {
        "level2":  "Tuân thủ quy định",
        "definition":  "Đồng phục đúng chuẩn",
        "id":  "COMP21",
        "level4":  "Huấn luyện, làm gương",
        "category":  "Hygiene \u0026 Bar Standards",
        "nameVi":  "Uniform",
        "name":  "Uniform",
        "evidence":  "Quan sát trực tiếp",
        "trainingMethod":  "SOP training, coaching",
        "level1":  "Mặc đầy đủ",
        "level3":  "Nhắc nhở team"
    },
    {
        "level2":  "Chủ động tiết kiệm",
        "definition":  "Sử dụng nguyên vật liệu hợp lý",
        "id":  "COMP22",
        "level4":  "Phân tích, tối ưu toàn bar",
        "category":  "Hygiene \u0026 Bar Standards",
        "nameVi":  "Efficiency in controlling and using ingredients",
        "name":  "Efficiency in controlling and using ingredients",
        "evidence":  "Inventory check, kiểm tra thực tế",
        "trainingMethod":  "Coaching, SOP",
        "level1":  "Theo hướng dẫn",
        "level3":  "Nhăc nhở team"
    },
    {
        "level2":  "Sắp xếp chuẩn, gọn",
        "definition":  "Sắp xếp quầy hợp lý",
        "id":  "COMP23",
        "level4":  "Huấn luyện chuẩn toàn bar",
        "category":  "Hygiene \u0026 Bar Standards",
        "nameVi":  "Arrange bar station logically and neatly",
        "name":  "Arrange bar station logically and neatly",
        "evidence":  "Quan sát, checklist SOPs, SSOPs",
        "trainingMethod":  "Coaching",
        "level1":  "Hướng dẫn sắp xếp cơ bản",
        "level3":  "Giám sát team"
    },
    {
        "level2":  "Chủ động thực hiện",
        "definition":  "Tuân thủ VSATTP",
        "id":  "COMP24",
        "level4":  "Huấn luyện chuẩn HACCP/5S",
        "category":  "Hygiene \u0026 Bar Standards",
        "nameVi":  "Follow Food and Safety Standards",
        "name":  "Follow Food and Safety Standards",
        "evidence":  "Quan sát thực tế, kết quả audit cửa hàng: QC, DM/SWATT",
        "trainingMethod":  "SOP training, coaching",
        "level1":  "Theo hướng dẫn",
        "level3":  "Giám sát team"
    },
    {
        "level2":  "Kiểm tra và tuân thủ",
        "definition":  "Tuân thủ hạn sử dụng",
        "id":  "COMP25",
        "level4":  "Huấn luyện SOP",
        "category":  "Hygiene \u0026 Bar Standards",
        "nameVi":  "Control and use items following expired date",
        "name":  "Control and use items following expired date",
        "evidence":  "Quan sát thực tế, kết quả audit cửa hàng: QC, DM/SWATT",
        "trainingMethod":  "SOP training",
        "level1":  "Theo hướng dẫn",
        "level3":  " Nhắc nhở team"
    },
    {
        "level2":  "Thực hiện đúng định kỳ",
        "definition":  "Vệ sinh máy móc, công cụ",
        "id":  "COMP26",
        "level4":  "Huấn luyện chuẩn",
        "category":  "Hygiene \u0026 Bar Standards",
        "nameVi":  "Tools and equipment cleaning",
        "name":  "Tools and equipment cleaning",
        "evidence":  "Quan sát thực tế, kết quả audit cửa hàng: QC, DM/SWATT",
        "trainingMethod":  "SOP training, coaching",
        "level1":  "Theo hướng dẫn",
        "level3":  "Giám sát team"
    },
    {
        "level2":  "Thực hiện đầy đủ",
        "definition":  "Bảo quản nguyên liệu đúng chuẩn",
        "id":  "COMP27",
        "level4":  "Huấn luyện chuẩn",
        "category":  "Hygiene \u0026 Bar Standards",
        "nameVi":  "Preserve ingredient following standard",
        "name":  "Preserve ingredient following standard",
        "evidence":  "Quan sát thực tế, kết quả audit cửa hàng: QC, DM/SWATT",
        "trainingMethod":  "SOP training",
        "level1":  "Theo hướng dẫn",
        "level3":  "Giám sát team"
    },
    {
        "level2":  "Thực hiện ổn định",
        "definition":  "Quản lý đồ ra quầy \u0026 phối hợp với bar",
        "id":  "COMP28",
        "level4":  "Huấn luyện chuẩn khu vực",
        "category":  "Leadership \u0026 Personal Development/ Other Skills",
        "nameVi":  "Expo skill (control TST, TPT, etc)",
        "name":  "Expo skill (control TST, TPT, etc)",
        "evidence":  "Quan sát thực tế",
        "trainingMethod":  "Coaching, shadowing",
        "level1":  "Hỗ trợ theo hướng dẫn",
        "level3":  "Giám sát, hướng dẫn team"
    },
    {
        "level2":  "Thực hiện đúng",
        "definition":  "Đặt hàng trên Netsuite",
        "id":  "COMP29",
        "level4":  "Huấn luyện team",
        "category":  "Leadership \u0026 Personal Development/ Other Skills",
        "nameVi":  "Netsuite order skill",
        "name":  "Netsuite order skill",
        "evidence":  "Kiểm tra thực tế thao tác đơn hàng",
        "trainingMethod":  "Coaching",
        "level1":  "Theo hướng dẫn",
        "level3":  "Giám sát, hướng dẫn"
    },
    {
        "level2":  "Hướng dẫn Barista mới, hỗ trợ đồng đội",
        "definition":  "Đào tạo nhân viên",
        "id":  "COMP30",
        "level4":  "Đào tạo nhóm, đánh giá hiệu quả học tập",
        "category":  "Leadership \u0026 Personal Development/ Other Skills",
        "nameVi":  "Coaching \u0026 Training Skill",
        "name":  "Coaching \u0026 Training Skill",
        "evidence":  "Training Method: On-the-job, shadowing, train-the-trainer\nEvidence / Observable: Quan sát hướng dẫn, feedback học viên, số lượng nhân viên được coaching\nEvaluation: Feedback từ học viên, kiểm tra năng lực sau đào tạo",
        "trainingMethod":  "Có khả năng Train-the-trainer, shadow MB Trainer Internal cho cửa hàng",
        "level1":  "Chia sẻ kinh nghiệm nhỏ với đồng nghiệp",
        "level3":  "Đào tạo nhóm"
    },
    {
        "level2":  "Kiểm kê cơ bản",
        "definition":  "Quản lý tồn kho",
        "id":  "COMP31",
        "level4":  "Phân tích \u0026 tối ưu inventory",
        "category":  "Leadership \u0026 Personal Development/ Other Skills",
        "nameVi":  "Inventory skill",
        "name":  "Inventory skill",
        "evidence":  "Inventory check, kiểm tra thực tế",
        "trainingMethod":  "Coaching, SOP",
        "level1":  "Theo hướng dẫn",
        "level3":  "Giảm hao hụt chuẩn"
    },
    {
        "level2":  "Giải quyết tình huống đơn giản",
        "definition":  "Giải quyết vấn đề \u0026 phàn nàn khách",
        "id":  "COMP32",
        "level4":  "Biến phàn nàn thành cơ hội",
        "category":  "Leadership \u0026 Personal Development/ Other Skills",
        "nameVi":  "Xử lý tình huống \u0026 khiếu nại",
        "name":  "Xử lý tình huống \u0026 khiếu nại",
        "evidence":  "Feedback khách, quan sát",
        "trainingMethod":  "Roleplay, coaching",
        "level1":  "Báo cáo cấp trên",
        "level3":  "Chủ động xử lý 80% tình huống"
    },
    {
        "level2":  "Khích lệ trực tiếp",
        "definition":  "Khích lệ đồng đội \u0026 tạo văn hóa tích cực",
        "id":  "COMP33",
        "level4":  "Duy trì tinh thần \u0026 gắn kết toàn cửa hàng/khu vực",
        "category":  "Leadership \u0026 Personal Development/ Other Skills",
        "nameVi":  "Tạo động lực \u0026 gắn kết",
        "name":  "Tạo động lực \u0026 gắn kết",
        "evidence":  "Quan sát, feedback team",
        "trainingMethod":  "Coaching, shadowing",
        "level1":  "Gương mẫu",
        "level3":  "Tạo văn hóa bar"
    },
    {
        "level2":  "Đưa ra sáng kiến cải tiến hợp lý (ví dụ: Đề xuất cải tiến nhỏ, ví dụ sắp xếp nguyên liệu hợp lý hơn)",
        "definition":  "Chủ động cải tiến quy trình",
        "id":  "COMP34",
        "level4":  "Đóng góp cải tiến toàn bộ bar/khu vực, tham gia đóng góp mang tính cải tiến vận hạnh",
        "category":  "Leadership \u0026 Personal Development/ Other Skills",
        "nameVi":  "Tư duy cải tiến (CI Mindset)",
        "name":  "Tư duy cải tiến (CI Mindset)",
        "evidence":  "Checklist: thực hiện đúng SOPs, quan sát ca làm việc\nSố lượng ý tưởng được áp dụng; feedback SM/Trainer\nSố sáng kiến triển khai thành công; cải thiện KPI (tốc độ phục vụ, giảm lãng phí, tăng chất lượng)\nKết quả dự án cải tiến (ví dụ: giảm lãng phí 10%, tăng năng suất, phản hồi khách hàng tích cực)",
        "trainingMethod":  "Coaching \u0026 mentoring từ SM/Trainer: hỗ trợ phát triển ý tưởng, triển khai tại quầy bar,\nCross-bar / cross-store CI projects: tham gia cải tiến toàn khu vực, chia sẻ best practices.\n- Leadership coaching \u0026 CI review: hướng dẫn cách triển khai cải tiến trên diện rộng và đo lường kết quả.\n- Workshop brainstorming: nhân viên được hướng dẫn quan sát quy trình, xác định điểm chưa tối ưu.\n- Mini-project / Kaizen nhỏ: thử đề xuất cải tiến tại quầy của mình.\n- Học qua on-the-job training (thực hành theo SOP) để hiểu chuẩn công việc.\n- Quan sát quy trình chuẩn (shadowing MB) để biết “cách làm đúng”.",
        "level1":  "Thực hiện quy trình theo hướng dẫn, chấp nhận cách làm hiện tại",
        "level3":  "Thực hiện sáng kiến cải tiến tại khu vực, huấn luyện đồng đội áp dụng"
    },
    {
        "level2":  "Chủ động học công thức mới",
        "definition":  "Tiếp thu, học hỏi \u0026 thích nghi nhanh",
        "id":  "COMP35",
        "level4":  "Dẫn đầu xu hướng trong đội ngũ",
        "category":  "Leadership \u0026 Personal Development/ Other Skills",
        "nameVi":  "Khả năng học hỏi \u0026 thích nghi",
        "name":  "Khả năng học hỏi \u0026 thích nghi",
        "evidence":  "Quan sát học tập \u0026 áp dụng",
        "trainingMethod":  "Shadowing, training mới",
        "level1":  "Tiếp thu từ đồng nghiệp",
        "level3":  "Nhanh chóng nắm bắt \u0026 huấn luyện lại"
    },
    {
        "level2":  "Có trách nhiệm trong ca",
        "definition":  "Tuân thủ giờ giấc \u0026 trách nhiệm công việc",
        "id":  "COMP36",
        "level4":  "Truyền cảm hứng văn hóa Highlands",
        "category":  "Leadership \u0026 Personal Development/ Other Skills",
        "nameVi":  "Kỷ luật \u0026 trách nhiệm cá nhân",
        "name":  "Kỷ luật \u0026 trách nhiệm cá nhân",
        "evidence":  "Quan sát, attendance log, feedback team",
        "trainingMethod":  "Coaching, mentoring",
        "level1":  "Đi làm đúng giờ, tuân thủ cơ bản",
        "level3":  "Làm gương về kỷ luật \u0026 trách nhiệm"
    }
]
